{
  "type": "FeatureCollection",
  "features": [
    {
      "type": "Feature",
      "properties": {},
      "geometry": {
        "type": "Polygon",
        "coordinates": [
          [
            [
              -121.51634216308594,
              38.56212645363985
            ],
            [
              -121.56097412109375,
              38.56105262446978
            ],
            [
              -121.57333374023438,
              38.556757147352215
            ],
            [
              -121.58157348632811,
              38.54762840618704
            ],
            [
              -121.58569335937501,
              38.53259030590469
            ],
            [
              -121.5850067138672,
              38.47133130139452
            ],
            [
              -121.65092468261719,
              38.338963374634815
            ],
            [
              -121.67152404785156,
              38.25435798036572
            ],
            [
              -121.68525695800781,
              38.259210636396546
            ],
            [
              -121.68800354003906,
              38.26675856826527
            ],
            [
              -121.69281005859374,
              38.274844767832825
            ],
            [
              -121.70173645019531,
              38.28454701883166
            ],
            [
              -121.70791625976561,
              38.29370906531383
            ],
            [
              -121.71958923339842,
              38.298559092254344
            ],
            [
              -121.7401885986328,
              38.30071455572194
            ],
            [
              -121.76422119140625,
              38.297481336506095
            ],
            [
              -121.77932739257812,
              38.28885871419225
            ],
            [
              -121.79168701171875,
              38.275922859749215
            ],
            [
              -121.79443359375,
              38.25543637637947
            ],
            [
              -121.78619384765624,
              38.24357314004956
            ],
            [
              -121.76971435546874,
              38.24087667992996
            ],
            [
              -121.74842834472656,
              38.24087667992996
            ],
            [
              -121.72920227050781,
              38.23656213571519
            ],
            [
              -121.71615600585938,
              38.231168595418694
            ],
            [
              -121.71615600585938,
              38.22199865889175
            ],
            [
              -121.72576904296876,
              38.209590434272144
            ],
            [
              -121.72508239746095,
              38.203115738057605
            ],
            [
              -121.68251037597656,
              38.18854556604565
            ],
            [
              -121.67015075683594,
              38.182068998322094
            ],
            [
              -121.65985107421874,
              38.17019379541814
            ],
            [
              -121.63993835449219,
              38.16857429963515
            ],
            [
              -121.62689208984374,
              38.16209595668556
            ],
            [
              -121.6138458251953,
              38.16047628099622
            ],
            [
              -121.59530639648436,
              38.16425546830192
            ],
            [
              -121.58569335937501,
              38.171273439283084
            ],
            [
              -121.58157348632811,
              38.17937025849983
            ],
            [
              -121.56990051269533,
              38.18476763818223
            ],
            [
              -121.56166076660156,
              38.190704293996504
            ],
            [
              -121.55204772949217,
              38.1966404659587
            ],
            [
              -121.55204772949217,
              38.20473446610162
            ],
            [
              -121.54655456542969,
              38.21876193471268
            ],
            [
              -121.54655456542969,
              38.22793227923281
            ],
            [
              -121.53350830078124,
              38.23008983935712
            ],
            [
              -121.51908874511717,
              38.23062921938795
            ],
            [
              -121.51016235351562,
              38.236022799686666
            ],
            [
              -121.50604248046874,
              38.24249456800328
            ],
            [
              -121.5039825439453,
              38.25004423627535
            ],
            [
              -121.51222229003906,
              38.26298470036054
            ],
            [
              -121.52732849121094,
              38.273227599946274
            ],
            [
              -121.53419494628905,
              38.27969605540384
            ],
            [
              -121.54449462890625,
              38.293170153420135
            ],
            [
              -121.55754089355469,
              38.30448646269451
            ],
            [
              -121.55891418457031,
              38.31741722616914
            ],
            [
              -121.53076171875,
              38.33788621934407
            ],
            [
              -121.51016235351562,
              38.35350340353833
            ],
            [
              -121.50741577148439,
              38.36157993606723
            ],
            [
              -121.50810241699219,
              38.37503882134334
            ],
            [
              -121.50260925292967,
              38.3868805698475
            ],
            [
              -121.50192260742186,
              38.394953377817885
            ],
            [
              -121.50260925292967,
              38.406253794852674
            ],
            [
              -121.50535583496092,
              38.412172355881054
            ],
            [
              -121.5142822265625,
              38.42293213401053
            ],
            [
              -121.51565551757812,
              38.42831142210914
            ],
            [
              -121.50741577148439,
              38.429925130409366
            ],
            [
              -121.49368286132812,
              38.43422817624596
            ],
            [
              -121.4916229248047,
              38.441220078788945
            ],
            [
              -121.49093627929689,
              38.453588708941375
            ],
            [
              -121.49093627929689,
              38.47348162207647
            ],
            [
              -121.4923095703125,
              38.47616943274549
            ],
            [
              -121.50810241699219,
              38.48100723942962
            ],
            [
              -121.52664184570312,
              38.48100723942962
            ],
            [
              -121.53625488281249,
              38.485307239467645
            ],
            [
              -121.54518127441406,
              38.49713091673102
            ],
            [
              -121.54518127441406,
              38.50465406475561
            ],
            [
              -121.53144836425781,
              38.50895265368141
            ],
            [
              -121.5252685546875,
              38.50895265368141
            ],
            [
              -121.51908874511717,
              38.51486279448153
            ],
            [
              -121.51359558105469,
              38.521846880854994
            ],
            [
              -121.51359558105469,
              38.5256072620712
            ],
            [
              -121.51977539062499,
              38.529367446805786
            ],
            [
              -121.51016235351562,
              38.53366456019077
            ],
            [
              -121.50192260742186,
              38.53849850597664
            ],
            [
              -121.50192260742186,
              38.5535353710587
            ],
            [
              -121.50604248046874,
              38.56105262446978
            ],
            [
              -121.51634216308594,
              38.56212645363985
            ]
          ]
        ]
      }
    }
  ]
}
